LICENSE
MANIFEST.in
README.rst
setup.cfg
setup.py
django_graphql_social_auth_d4.egg-info/PKG-INFO
django_graphql_social_auth_d4.egg-info/SOURCES.txt
django_graphql_social_auth_d4.egg-info/dependency_links.txt
django_graphql_social_auth_d4.egg-info/not-zip-safe
django_graphql_social_auth_d4.egg-info/requires.txt
django_graphql_social_auth_d4.egg-info/top_level.txt
graphql_social_auth/__init__.py
graphql_social_auth/decorators.py
graphql_social_auth/exceptions.py
graphql_social_auth/mixins.py
graphql_social_auth/mutations.py
graphql_social_auth/types.py
graphql_social_auth/utils.py
graphql_social_auth/locale/es/LC_MESSAGES/django.mo
graphql_social_auth/locale/es/LC_MESSAGES/django.po
graphql_social_auth/relay/__init__.py
graphql_social_auth/relay/mutations.py
graphql_social_auth/relay/nodes.py