Metadata-Version: 2.1
Name: django-graphql-social-auth-d4
Version: 0.1.4
Summary: Python Social Auth support for Django GraphQL
Home-page: https://github.com/shuvoooo/django-graphql-social-auth/tree/patch-1
Author: shuvoo
Author-email: shuvo.punam@gmail.com
Maintainer: mongkok
License: MIT
Platform: UNKNOWN
Classifier: Development Status :: 4 - Beta
Classifier: Environment :: Web Environment
Classifier: Intended Audience :: Developers
Classifier: License :: OSI Approved :: MIT License
Classifier: Operating System :: OS Independent
Classifier: Programming Language :: Python
Classifier: Programming Language :: Python :: 3
Classifier: Programming Language :: Python :: 3.4
Classifier: Programming Language :: Python :: 3.5
Classifier: Programming Language :: Python :: 3.6
Classifier: Programming Language :: Python :: 3.7
Classifier: Framework :: Django
Classifier: Framework :: Django :: 1.11
Classifier: Framework :: Django :: 2.0
Classifier: Framework :: Django :: 2.1
Classifier: Framework :: Django :: 2.2
Provides-Extra: jwt
License-File: LICENSE
